<?xml version="1.0" encoding="UTF-8"?><gmd:MD_Metadata xmlns:gmd="http://www.isotc211.org/2005/gmd" xmlns:gco="http://www.isotc211.org/2005/gco" xmlns:geonet="http://www.fao.org/geonetwork" xmlns:gml="http://www.opengis.net/gml/3.2" xmlns:gmx="http://www.isotc211.org/2005/gmx" xmlns:xlink="http://www.w3.org/1999/xlink" xmlns:xsi="http://www.w3.org/2001/XMLSchema-instance" xsi:schemaLocation="http://www.isotc211.org/2005/gmd http://schemas.opengis.net/iso/19139/20070417/gmd/gmd.xsd http://www.isotc211.org/2005/gmx http://schemas.opengis.net/iso/19139/20070417/gmx/gmx.xsd http://www.isotc211.org/2005/srv http://schemas.opengis.net/iso/19139/20070417/srv/1.0/srv.xsd">
         <gmd:fileIdentifier>
            <gco:CharacterString>a249a90c-661c-46d7-8dfc-7cc172b75034</gco:CharacterString>
         </gmd:fileIdentifier>
         <gmd:language>
            <gmd:LanguageCode codeList="http://www.loc.gov/standards/iso639-2/" codeListValue="pol"/>
         </gmd:language>
         <gmd:characterSet>
            <gmd:MD_CharacterSetCode codeList="http://standards.iso.org/iso/19139/resources/gmxCodelists.xml#MD_CharacterSetCode" codeListValue="utf8"/>
         </gmd:characterSet>
         <gmd:hierarchyLevel>
            <gmd:MD_ScopeCode codeList="http://standards.iso.org/iso/19139/resources/gmxCodelists.xml#MD_ScopeCode" codeListValue="dataset"/>
         </gmd:hierarchyLevel>
         <gmd:contact>
            <gmd:CI_ResponsibleParty>
               <gmd:organisationName xsi:type="gmd:PT_FreeText_PropertyType">
                  <gco:CharacterString>Państwowe Gospodarstwo Wodne Wody Polskie</gco:CharacterString>
                  <gmd:PT_FreeText>
                     <gmd:textGroup>
                        <gmd:LocalisedCharacterString locale="#locale-eng">State Water Holding Polish Waters</gmd:LocalisedCharacterString>
                     </gmd:textGroup>
                  </gmd:PT_FreeText>
               </gmd:organisationName>
               <gmd:contactInfo>
                  <gmd:CI_Contact>
                     <gmd:phone>
                        <gmd:CI_Telephone>
                           <gmd:voice>
                              <gco:CharacterString>+48223720240</gco:CharacterString>
                           </gmd:voice>
                        </gmd:CI_Telephone>
                     </gmd:phone>
                     <gmd:address>
                        <gmd:CI_Address>
                           <gmd:electronicMailAddress>
                              <gco:CharacterString>inspire@wody.gov.pl</gco:CharacterString>
                           </gmd:electronicMailAddress>
                        </gmd:CI_Address>
                     </gmd:address>
                     <gmd:onlineResource>
                        <gmd:CI_OnlineResource>
                           <gmd:linkage>
                              <gmd:URL>http://www.wody.gov.pl/</gmd:URL>
                           </gmd:linkage>
                        </gmd:CI_OnlineResource>
                     </gmd:onlineResource>
                  </gmd:CI_Contact>
               </gmd:contactInfo>
               <gmd:role>
                  <gmd:CI_RoleCode codeList="http://standards.iso.org/iso/19139/resources/gmxCodelists.xml#CI_RoleCode" codeListValue="pointOfContact"/>
               </gmd:role>
            </gmd:CI_ResponsibleParty>
         </gmd:contact>
         <gmd:dateStamp>
            <gco:Date>2019-12-06</gco:Date>
         </gmd:dateStamp>
         <gmd:metadataStandardName>
            <gco:CharacterString>ISO 19115</gco:CharacterString>
         </gmd:metadataStandardName>
         <gmd:metadataStandardVersion>
            <gco:CharacterString>2003/cor.1:2006</gco:CharacterString>
         </gmd:metadataStandardVersion>
         <gmd:locale>
            <gmd:PT_Locale id="locale-eng">
               <gmd:languageCode>
                  <gmd:LanguageCode codeList="http://www.loc.gov/standards/iso639-2/" codeListValue="eng"/>
               </gmd:languageCode>
               <gmd:characterEncoding>
                  <gmd:MD_CharacterSetCode codeList="http://standards.iso.org/iso/19139/resources/gmxCodelists.xml#MD_CharacterSetCode" codeListValue="utf8"/>
               </gmd:characterEncoding>
            </gmd:PT_Locale>
         </gmd:locale>
         <gmd:referenceSystemInfo>
            <gmd:MD_ReferenceSystem>
               <gmd:referenceSystemIdentifier>
                  <gmd:RS_Identifier>
                     <gmd:code>
                        <gmx:Anchor xlink:href="http://www.opengis.net/def/crs/EPSG/0/4258">4258</gmx:Anchor>
                     </gmd:code>
                  </gmd:RS_Identifier>
               </gmd:referenceSystemIdentifier>
            </gmd:MD_ReferenceSystem>
         </gmd:referenceSystemInfo>
         <gmd:identificationInfo>
            <gmd:MD_DataIdentification id="SU_2016">
               <gmd:citation>
                  <gmd:CI_Citation>
                     <gmd:title xsi:type="gmd:PT_FreeText_PropertyType">
                        <gco:CharacterString>Podjednostki obszarów dorzeczy</gco:CharacterString>
                        <gmd:PT_FreeText>
                           <gmd:textGroup>
                              <gmd:LocalisedCharacterString locale="#locale-eng">River basin districts sub-units</gmd:LocalisedCharacterString>
                           </gmd:textGroup>
                        </gmd:PT_FreeText>
                     </gmd:title>
                     <gmd:date>
                        <gmd:CI_Date>
                           <gmd:date>
                              <gco:Date>2019-12-10</gco:Date>
                           </gmd:date>
                           <gmd:dateType>
                              <gmd:CI_DateTypeCode codeList="http://standards.iso.org/iso/19139/resources/gmxCodelists.xml#CI_DateTypeCode" codeListValue="publication"/>
                           </gmd:dateType>
                        </gmd:CI_Date>
                     </gmd:date>
                     <gmd:identifier>
                        <gmd:MD_Identifier>
                           <gmd:code>
                              <gco:CharacterString>http://iip.wody.gov.pl/id/dataset/PL.ZIPGW.6439/SU_2016</gco:CharacterString>
                           </gmd:code>
                        </gmd:MD_Identifier>
                     </gmd:identifier>
                  </gmd:CI_Citation>
               </gmd:citation>
               <gmd:abstract xsi:type="gmd:PT_FreeText_PropertyType">
                  <gco:CharacterString>Podjednostki obszarów dorzeczy, wyznaczone na potrzeby sporządzenia planów gospodarowania wodami na obszarach dorzeczy.</gco:CharacterString>
                  <gmd:PT_FreeText>
                     <gmd:textGroup>
                        <gmd:LocalisedCharacterString locale="#locale-eng">River basin districts sub-units, established for river basin management plans.</gmd:LocalisedCharacterString>
                     </gmd:textGroup>
                  </gmd:PT_FreeText>
               </gmd:abstract>
               <gmd:pointOfContact>
                  <gmd:CI_ResponsibleParty>
                     <gmd:organisationName xsi:type="gmd:PT_FreeText_PropertyType">
                        <gco:CharacterString>Państwowe Gospodarstwo Wodne Wody Polskie</gco:CharacterString>
                        <gmd:PT_FreeText>
                           <gmd:textGroup>
                              <gmd:LocalisedCharacterString locale="#locale-eng">State Water Holding Polish Waters</gmd:LocalisedCharacterString>
                           </gmd:textGroup>
                        </gmd:PT_FreeText>
                     </gmd:organisationName>
                     <gmd:contactInfo>
                        <gmd:CI_Contact>
                           <gmd:phone>
                              <gmd:CI_Telephone>
                                 <gmd:voice>
                                    <gco:CharacterString>+48223720240</gco:CharacterString>
                                 </gmd:voice>
                              </gmd:CI_Telephone>
                           </gmd:phone>
                           <gmd:address>
                              <gmd:CI_Address>
                                 <gmd:electronicMailAddress>
                                    <gco:CharacterString>inspire@wody.gov.pl</gco:CharacterString>
                                 </gmd:electronicMailAddress>
                              </gmd:CI_Address>
                           </gmd:address>
                           <gmd:onlineResource>
                              <gmd:CI_OnlineResource>
                                 <gmd:linkage>
                                    <gmd:URL>http://www.wody.gov.pl/</gmd:URL>
                                 </gmd:linkage>
                              </gmd:CI_OnlineResource>
                           </gmd:onlineResource>
                        </gmd:CI_Contact>
                     </gmd:contactInfo>
                     <gmd:role>
                        <gmd:CI_RoleCode codeList="http://standards.iso.org/iso/19139/resources/gmxCodelists.xml#CI_RoleCode" codeListValue="owner"/>
                     </gmd:role>
                  </gmd:CI_ResponsibleParty>
               </gmd:pointOfContact>
               <gmd:resourceMaintenance>
                  <gmd:MD_MaintenanceInformation>
                     <gmd:maintenanceAndUpdateFrequency>
                        <gmd:MD_MaintenanceFrequencyCode codeList="http://standards.iso.org/iso/19139/resources/gmxCodelists.xml#MD_MaintenanceFrequencyCode" codeListValue="asNeeded"/>
                     </gmd:maintenanceAndUpdateFrequency>
                     <gmd:updateScope>
                        <gmd:MD_ScopeCode codeList="http://standards.iso.org/iso/19139/resources/gmxCodelists.xml#MD_ScopeCode" codeListValue="dataset"/>
                     </gmd:updateScope>
                     <gmd:maintenanceNote xsi:type="gmd:PT_FreeText_PropertyType">
                        <gco:CharacterString>Tryb aktualizacji nie jest znany</gco:CharacterString>
                        <gmd:PT_FreeText>
                           <gmd:textGroup>
                              <gmd:LocalisedCharacterString locale="#locale-eng">Tryb aktualizacji nie jest znany</gmd:LocalisedCharacterString>
                           </gmd:textGroup>
                        </gmd:PT_FreeText>
                     </gmd:maintenanceNote>
                  </gmd:MD_MaintenanceInformation>
               </gmd:resourceMaintenance>
               <gmd:descriptiveKeywords>
                  <gmd:MD_Keywords>
                     <gmd:keyword>
                        <gmx:Anchor xlink:href="http://inspire.ec.europa.eu/theme/am">Gospodarowanie obszarem/strefy ograniczone/regulacyjne oraz jednostki sprawozdawcze</gmx:Anchor>
                     </gmd:keyword>
                     <gmd:thesaurusName>
                        <gmd:CI_Citation>
                           <gmd:title>
                              <gmx:Anchor xlink:href="http://www.eionet.europa.eu/gemet/inspire_themes">GEMET - INSPIRE themes, version 1.0</gmx:Anchor>
                           </gmd:title>
                           <gmd:date>
                              <gmd:CI_Date>
                                 <gmd:date>
                                    <gco:Date>2008-06-01</gco:Date>
                                 </gmd:date>
                                 <gmd:dateType>
                                    <gmd:CI_DateTypeCode codeList="http://standards.iso.org/iso/19139/resources/gmxCodelists.xml#CI_DateTypeCode" codeListValue="publication"/>
                                 </gmd:dateType>
                              </gmd:CI_Date>
                           </gmd:date>
                           <gmd:edition>
                              <gco:CharacterString>1.0</gco:CharacterString>
                           </gmd:edition>
                        </gmd:CI_Citation>
                     </gmd:thesaurusName>
                  </gmd:MD_Keywords>
               </gmd:descriptiveKeywords>
               <gmd:descriptiveKeywords>
                  <gmd:MD_Keywords>
                     <gmd:keyword>
                        <gmx:Anchor xlink:href="http://inspire.ec.europa.eu/metadata-codelist/SpatialScope/national">Krajowe</gmx:Anchor>
                     </gmd:keyword>
                     <gmd:thesaurusName>
                        <gmd:CI_Citation>
                           <gmd:title>
                              <gmx:Anchor xlink:href="http://inspire.ec.europa.eu/metadata-codelist/SpatialScope">Zakres przestrzenny</gmx:Anchor>
                           </gmd:title>
                           <gmd:date>
                              <gmd:CI_Date>
                                 <gmd:date>
                                    <gco:Date>2019-05-22</gco:Date>
                                 </gmd:date>
                                 <gmd:dateType>
                                    <gmd:CI_DateTypeCode codeList="http://standards.iso.org/iso/19139/resources/gmxCodelists.xml#CI_DateTypeCode" codeListValue="publication"/>
                                 </gmd:dateType>
                              </gmd:CI_Date>
                           </gmd:date>
                        </gmd:CI_Citation>
                     </gmd:thesaurusName>
                  </gmd:MD_Keywords>
               </gmd:descriptiveKeywords>
               <gmd:descriptiveKeywords>
                  <gmd:MD_Keywords>
                     <gmd:keyword>
                        <gmx:Anchor xlink:href="http://inspire.ec.europa.eu/metadata-codelist/PriorityDataset/RiverBasinDistrictsSubUnits-dir-2000-60">River basin districts sub-units (Water Framework Directive)</gmx:Anchor>
                     </gmd:keyword>
                     <gmd:thesaurusName>
                        <gmd:CI_Citation>
                           <gmd:title>
                              <gmx:Anchor xlink:href="http://inspire.ec.europa.eu/metadata-codelist/PriorityDataset">INSPIRE priority data set, v2.0</gmx:Anchor>
                           </gmd:title>
                           <gmd:date>
                              <gmd:CI_Date>
                                 <gmd:date>
                                    <gco:Date>2018-04-04</gco:Date>
                                 </gmd:date>
                                 <gmd:dateType>
                                    <gmd:CI_DateTypeCode codeList="http://standards.iso.org/iso/19139/resources/gmxCodelists.xml#CI_DateTypeCode" codeListValue="publication"/>
                                 </gmd:dateType>
                              </gmd:CI_Date>
                           </gmd:date>
                        </gmd:CI_Citation>
                     </gmd:thesaurusName>
                  </gmd:MD_Keywords>
               </gmd:descriptiveKeywords>
               <gmd:descriptiveKeywords>
                  <gmd:MD_Keywords>
                     <gmd:keyword xsi:type="gmd:PT_FreeText_PropertyType">
                        <gco:CharacterString>gospodarka wodna</gco:CharacterString>
                        <gmd:PT_FreeText>
                           <gmd:textGroup>
                              <gmd:LocalisedCharacterString locale="#locale-eng">water management</gmd:LocalisedCharacterString>
                           </gmd:textGroup>
                        </gmd:PT_FreeText>
                     </gmd:keyword>
                     <gmd:keyword xsi:type="gmd:PT_FreeText_PropertyType">
                        <gco:CharacterString>wody śródlądowe</gco:CharacterString>
                        <gmd:PT_FreeText>
                           <gmd:textGroup>
                              <gmd:LocalisedCharacterString locale="#locale-eng">inland waters</gmd:LocalisedCharacterString>
                           </gmd:textGroup>
                        </gmd:PT_FreeText>
                     </gmd:keyword>
                     <gmd:keyword>
                        <gco:CharacterString>Inspire</gco:CharacterString>
                     </gmd:keyword>
                  </gmd:MD_Keywords>
               </gmd:descriptiveKeywords>
               <gmd:resourceConstraints>
                  <gmd:MD_LegalConstraints>
                     <gmd:accessConstraints>
                        <gmd:MD_RestrictionCode codeList="http://standards.iso.org/iso/19139/resources/gmxCodelists.xml#MD_RestrictionCode" codeListValue="otherRestrictions"/>
                     </gmd:accessConstraints>
                     <gmd:otherConstraints>
                        <gmx:Anchor xlink:href="http://inspire.ec.europa.eu/metadata-codelist/LimitationsOnPublicAccess/noLimitations">Brak ograniczeń w publicznym dostępie</gmx:Anchor>
                     </gmd:otherConstraints>
                  </gmd:MD_LegalConstraints>
               </gmd:resourceConstraints>
               <gmd:resourceConstraints>
                  <gmd:MD_LegalConstraints>
                     <gmd:useConstraints>
                        <gmd:MD_RestrictionCode codeList="http://standards.iso.org/iso/19139/resources/gmxCodelists.xml#MD_RestrictionCode" codeListValue="otherRestrictions"/>
                     </gmd:useConstraints>
                     <gmd:otherConstraints>
                        <gmx:Anchor xlink:href="http://inspire.ec.europa.eu/metadata-codelist/ConditionsApplyingToAccessAndUse/noConditionsApply">Brak warunków dostępu i użytkowania</gmx:Anchor>
                     </gmd:otherConstraints>
                  </gmd:MD_LegalConstraints>
               </gmd:resourceConstraints>
               <gmd:spatialRepresentationType>
                  <gmd:MD_SpatialRepresentationTypeCode codeList="http://standards.iso.org/ittf/PubliclyAvailableStandards/ISO_19139_Schemas/resources/codelist/ML_gmxCodelists.xml#MD_SpatialRepresentationTypeCode" codeListValue="vector"/>
               </gmd:spatialRepresentationType>
               <gmd:language>
                  <gmd:LanguageCode codeList="http://www.loc.gov/standards/iso639-2/" codeListValue="pol"/>
               </gmd:language>
               <gmd:characterSet>
                  <gmd:MD_CharacterSetCode codeList="http://standards.iso.org/iso/19139/resources/gmxCodelists.xml#MD_CharacterSetCode" codeListValue="utf8"/>
               </gmd:characterSet>
               <gmd:topicCategory>
                  <gmd:MD_TopicCategoryCode>planningCadastre</gmd:MD_TopicCategoryCode>
               </gmd:topicCategory>
               <gmd:extent>
                  <gmd:EX_Extent>
                     <gmd:geographicElement>
                        <gmd:EX_GeographicBoundingBox>
                           <gmd:westBoundLongitude>
                              <gco:Decimal>14.1228</gco:Decimal>
                           </gmd:westBoundLongitude>
                           <gmd:eastBoundLongitude>
                              <gco:Decimal>24.1458</gco:Decimal>
                           </gmd:eastBoundLongitude>
                           <gmd:southBoundLatitude>
                              <gco:Decimal>49.0020</gco:Decimal>
                           </gmd:southBoundLatitude>
                           <gmd:northBoundLatitude>
                              <gco:Decimal>54.8358</gco:Decimal>
                           </gmd:northBoundLatitude>
                        </gmd:EX_GeographicBoundingBox>
                     </gmd:geographicElement>
                     <gmd:temporalElement>
                        <gmd:EX_TemporalExtent>
                           <gmd:extent>
                              <gml:TimePeriod>
                                 <gml:beginPosition>2016-01-01</gml:beginPosition>
                                 <gml:endPosition>2021-12-31</gml:endPosition>
                              </gml:TimePeriod>
                           </gmd:extent>
                        </gmd:EX_TemporalExtent>
                     </gmd:temporalElement>
                  </gmd:EX_Extent>
               </gmd:extent>
            </gmd:MD_DataIdentification>
         </gmd:identificationInfo>
         <gmd:distributionInfo>
            <gmd:MD_Distribution>
               <gmd:distributionFormat>
                  <gmd:MD_Format>
                     <gmd:name>
                        <gco:CharacterString>Area management/restriction/regulation zones and reporting units GML Application Schema</gco:CharacterString>
                     </gmd:name>
                     <gmd:version>
                        <gco:CharacterString>4.0</gco:CharacterString>
                     </gmd:version>
                     <gmd:specification>
                        <gco:CharacterString>D2.8.III.11 INSPIRE Data Specification on Area Management/Restriction/Regulation Zones and Reporting Units – Technical Guidelines</gco:CharacterString>
                     </gmd:specification>
                  </gmd:MD_Format>
               </gmd:distributionFormat>
               <gmd:transferOptions>
                  <gmd:MD_DigitalTransferOptions>
                     <gmd:onLine>
                        <gmd:CI_OnlineResource>
                           <gmd:linkage>
                              <gmd:URL>https://wody.isok.gov.pl/atom_web/atom/INSPIRE_SU_2016</gmd:URL>
                           </gmd:linkage>
                           <gmd:name xsi:type="gmd:PT_FreeText_PropertyType">
                              <gco:CharacterString>Polska usługa pobierania ATOM dla zbioru podjednostek obszarów dorzeczy</gco:CharacterString>
                              <gmd:PT_FreeText>
                                 <gmd:textGroup>
                                    <gmd:LocalisedCharacterString locale="#locale-eng">The Polish ATOM feed download service of river basins sub-units dataset</gmd:LocalisedCharacterString>
                                 </gmd:textGroup>
                              </gmd:PT_FreeText>
                           </gmd:name>
                           <gmd:description xsi:type="gmd:PT_FreeText_PropertyType">
                              <gco:CharacterString>Usługa umożliwiająca pobieranie danych ze zbioru podjednostek obszarów dorzeczy dla obszaru Polski. Dane publikowane przez usługę zostały wygenerowane na podstawie polskich planów gospodarowania wodami na obszarach dorzeczy na lata 2016-2021. Usługa wykorzystuje interfejs Atom w wersji 1.0</gco:CharacterString>
                              <gmd:PT_FreeText>
                                 <gmd:textGroup>
                                    <gmd:LocalisedCharacterString locale="#locale-eng">This service enables download the polish river basin districts sub-units. Data come from the polish river basin managment plans database. The service uses the Atom 1.0 interface.</gmd:LocalisedCharacterString>
                                 </gmd:textGroup>
                              </gmd:PT_FreeText>
                           </gmd:description>
                           <gmd:function>
                              <gmd:CI_OnLineFunctionCode codeList="http://standards.iso.org/iso/19139/resources/gmxCodelists.xml#CI_OnLineFunctionCode" codeListValue="download"/>
                           </gmd:function>
                        </gmd:CI_OnlineResource>
                     </gmd:onLine>
                  </gmd:MD_DigitalTransferOptions>
               </gmd:transferOptions>
            </gmd:MD_Distribution>
         </gmd:distributionInfo>
         <gmd:dataQualityInfo>
            <gmd:DQ_DataQuality>
               <gmd:scope>
                  <gmd:DQ_Scope>
                     <gmd:level>
                        <gmd:MD_ScopeCode codeList="http://standards.iso.org/iso/19139/resources/gmxCodelists.xml#MD_ScopeCode" codeListValue="dataset"/>
                     </gmd:level>
                  </gmd:DQ_Scope>
               </gmd:scope>
               <gmd:report>
                  <gmd:DQ_DomainConsistency>
                     <gmd:result>
                        <gmd:DQ_ConformanceResult>
                           <gmd:specification>
                              <gmd:CI_Citation>
                                 <gmd:title>
                                    <gco:CharacterString>INSPIRE Data Specification on Area Management/Restriction/Regulation Zones and Reporting Units – Technical Guidelines, version 3.0</gco:CharacterString>
                                 </gmd:title>
                                 <gmd:date>
                                    <gmd:CI_Date>
                                       <gmd:date>
                                          <gco:Date>2013-12-10</gco:Date>
                                       </gmd:date>
                                       <gmd:dateType>
                                          <gmd:CI_DateTypeCode codeList="http://standards.iso.org/iso/19139/resources/gmxCodelists.xml#CI_DateTypeCode" codeListValue="publication"/>
                                       </gmd:dateType>
                                    </gmd:CI_Date>
                                 </gmd:date>
                              </gmd:CI_Citation>
                           </gmd:specification>
                           <gmd:explanation>
                              <gmx:Anchor xlink:href="http://inspire.ec.europa.eu/metadata-codelist/DegreeOfConformity/conformant">Zbiór danych jest zgodny z zestawem testów abstrakcyjnych zdefiniowanych w aneksie A dokumentu D2.8.III.11 INSPIRE Data Specification on Area Management/Restriction/Regulation Zones and Reporting Units – Technical Guidelines</gmx:Anchor>
                           </gmd:explanation>
                           <gmd:pass>
                              <gco:Boolean>true</gco:Boolean>
                           </gmd:pass>
                        </gmd:DQ_ConformanceResult>
                     </gmd:result>
                  </gmd:DQ_DomainConsistency>
               </gmd:report>
               <gmd:report>
                  <gmd:DQ_DomainConsistency>
                     <gmd:result>
                        <gmd:DQ_ConformanceResult>
                           <gmd:specification>
                              <gmd:CI_Citation>
                                 <gmd:title>
                                    <gmx:Anchor xlink:href="http://data.europa.eu/eli/reg/2010/1089">Rozporządzenie Komisji (UE) Nr 1089/2010 z dnia 23 listopada 2010 r. w sprawie wykonania dyrektywy 2007/2/WE Parlamentu Europejskiego i Rady w zakresie interoperacyjności zbiorów i usług danych przestrzennych</gmx:Anchor>
                                 </gmd:title>
                                 <gmd:date>
                                    <gmd:CI_Date>
                                       <gmd:date>
                                          <gco:Date>2010-12-08</gco:Date>
                                       </gmd:date>
                                       <gmd:dateType>
                                          <gmd:CI_DateTypeCode codeList="http://standards.iso.org/ittf/PubliclyAvailableStandards/ISO_19139_Schemas/resources/codelist/ML_gmxCodelists.xml#CI_DateTypeCode" codeListValue="publication"/>
                                       </gmd:dateType>
                                    </gmd:CI_Date>
                                 </gmd:date>
                              </gmd:CI_Citation>
                           </gmd:specification>
                           <gmd:explanation>
                              <gmx:Anchor xlink:href="http://inspire.ec.europa.eu/metadata-codelist/DegreeOfConformity/conformant">Zbiór danych jest zgodny z wymaganiami INSPIRE dotyczącymi interoperacyjności zbiorów i usług danych przestrzennych.</gmx:Anchor>
                           </gmd:explanation>
                           <gmd:pass>
                              <gco:Boolean>true</gco:Boolean>
                           </gmd:pass>
                        </gmd:DQ_ConformanceResult>
                     </gmd:result>
                  </gmd:DQ_DomainConsistency>
               </gmd:report>
               <gmd:lineage>
                  <gmd:LI_Lineage>
                     <gmd:statement xsi:type="gmd:PT_FreeText_PropertyType">
                        <gco:CharacterString>Dane pochodzą z bazy danych planów gospodarowania wodami na obszarach dorzeczy.</gco:CharacterString>
                        <gmd:PT_FreeText>
                           <gmd:textGroup>
                              <gmd:LocalisedCharacterString locale="#locale-eng">Data come from the river basin managment plans database.</gmd:LocalisedCharacterString>
                           </gmd:textGroup>
                        </gmd:PT_FreeText>
                     </gmd:statement>
                  </gmd:LI_Lineage>
               </gmd:lineage>
            </gmd:DQ_DataQuality>
         </gmd:dataQualityInfo>
      </gmd:MD_Metadata>