<?xml version="1.0" encoding="UTF-8"?><gmd:MD_Metadata xmlns:gmd="http://www.isotc211.org/2005/gmd" xmlns:gco="http://www.isotc211.org/2005/gco" xmlns:geonet="http://www.fao.org/geonetwork" xmlns:gml="http://www.opengis.net/gml" xmlns:gmx="http://www.isotc211.org/2005/gmx" xmlns:xlink="http://www.w3.org/1999/xlink" xmlns:xsi="http://www.w3.org/2001/XMLSchema-instance" xsi:schemaLocation="http://www.isotc211.org/2005/gmd http://schemas.opengis.net/iso/19139/20070417/gmd/gmd.xsd">
         <gmd:fileIdentifier>
            <gco:CharacterString>f00f3416-2904-47ad-81c1-c51f36449404</gco:CharacterString>
         </gmd:fileIdentifier>
         <gmd:language>
            <gmd:LanguageCode codeList="http://www.loc.gov/standards/iso639-2/" codeListValue="por" codeSpace="ISO 639-2">Português</gmd:LanguageCode>
         </gmd:language>
         <gmd:characterSet>
            <gmd:MD_CharacterSetCode codeList="http://standards.iso.org/ittf/PubliclyAvailableStandards/ISO_19139_Schemas/resources/codelist/gmxCodelists.xml#MD_CharacterSetCode" codeListValue="utf8">utf8</gmd:MD_CharacterSetCode>
         </gmd:characterSet>
         <gmd:hierarchyLevel>
            <gmd:MD_ScopeCode codeList="http://standards.iso.org/ittf/PubliclyAvailableStandards/ISO_19139_Schemas/resources/codelist/gmxCodelists.xml#MD_ScopeCode" codeListValue="series">Série</gmd:MD_ScopeCode>
         </gmd:hierarchyLevel>
         <gmd:hierarchyLevelName>
            <gco:CharacterString>Séries de dados geográficos</gco:CharacterString>
         </gmd:hierarchyLevelName>
         <gmd:contact>
            <gmd:CI_ResponsibleParty>
               <gmd:individualName>
                  <gco:CharacterString>Direção Técnica</gco:CharacterString>
               </gmd:individualName>
               <gmd:organisationName>
                  <gco:CharacterString>Instituto Hidrográfico</gco:CharacterString>
               </gmd:organisationName>
               <gmd:contactInfo>
                  <gmd:CI_Contact>
                     <gmd:address>
                        <gmd:CI_Address>
                           <gmd:deliveryPoint>
                              <gco:CharacterString>Rua das Trinas, 49</gco:CharacterString>
                           </gmd:deliveryPoint>
                           <gmd:city>
                              <gco:CharacterString>Lisboa</gco:CharacterString>
                           </gmd:city>
                           <gmd:postalCode>
                              <gco:CharacterString>1249-093</gco:CharacterString>
                           </gmd:postalCode>
                           <gmd:country>
                              <gco:CharacterString>Portugal</gco:CharacterString>
                           </gmd:country>
                           <gmd:electronicMailAddress>
                              <gco:CharacterString>ih.snig.metadados@hidrografico.pt</gco:CharacterString>
                           </gmd:electronicMailAddress>
                        </gmd:CI_Address>
                     </gmd:address>
                  </gmd:CI_Contact>
               </gmd:contactInfo>
               <gmd:role>
                  <gmd:CI_RoleCode codeList="http://www.isotc211.org/2005/resources/Codelist/gmxCodelists.xml#CI_RoleCode" codeListValue="pointOfContact" codeSpace="ISOTC211/19115">Contacto</gmd:CI_RoleCode>
               </gmd:role>
            </gmd:CI_ResponsibleParty>
         </gmd:contact>
         <gmd:dateStamp>
            <gco:Date>2020-11-25</gco:Date>
         </gmd:dateStamp>
         <gmd:metadataStandardName>
            <gco:CharacterString>ISO 19115 Sistema de Metadados dos Açores</gco:CharacterString>
         </gmd:metadataStandardName>
         <gmd:metadataStandardVersion>
            <gco:CharacterString>v.0.9.3</gco:CharacterString>
         </gmd:metadataStandardVersion>
         <gmd:referenceSystemInfo>
            <gmd:MD_ReferenceSystem>
               <gmd:referenceSystemIdentifier>
                  <gmd:RS_Identifier>
                     <gmd:code>
                        <gco:CharacterString>4326</gco:CharacterString>
                     </gmd:code>
                     <gmd:codeSpace>
                        <gco:CharacterString>EPSG</gco:CharacterString>
                     </gmd:codeSpace>
                  </gmd:RS_Identifier>
               </gmd:referenceSystemIdentifier>
            </gmd:MD_ReferenceSystem>
         </gmd:referenceSystemInfo>
         <gmd:identificationInfo>
            <gmd:MD_DataIdentification>
               <gmd:citation>
                  <gmd:CI_Citation>
                     <gmd:title xsi:type="gmd:PT_FreeText_PropertyType">
                        <gco:CharacterString>Cobertura dos Sedimentos Superficiais da Plataforma Continental Portuguesa (Corresponde às cartas SEPLAT)</gco:CharacterString>
                        <gmd:PT_FreeText>
                           <gmd:textGroup>
                              <gmd:LocalisedCharacterString locale="#locale-eng">Map of the Superficial Sediments of the Portuguese Continental Shelf</gmd:LocalisedCharacterString>
                           </gmd:textGroup>
                        </gmd:PT_FreeText>
                     </gmd:title>
                     <gmd:alternateTitle>
                        <gco:CharacterString>Cobertura SEPLAT</gco:CharacterString>
                     </gmd:alternateTitle>
                     <gmd:date>
                        <gmd:CI_Date>
                           <gmd:date>
                              <gco:Date>1985-01-01</gco:Date>
                           </gmd:date>
                           <gmd:dateType>
                              <gmd:CI_DateTypeCode codeList="http://standards.iso.org/ittf/PubliclyAvailableStandards/ISO_19139_Schemas/resources/codelist/gmxCodelists.xml#CI_DateTypeCode" codeListValue="creation">Criação</gmd:CI_DateTypeCode>
                           </gmd:dateType>
                        </gmd:CI_Date>
                     </gmd:date>
                     <gmd:date>
                        <gmd:CI_Date>
                           <gmd:date>
                              <gco:Date>2010-12-01</gco:Date>
                           </gmd:date>
                           <gmd:dateType>
                              <gmd:CI_DateTypeCode codeList="http://standards.iso.org/ittf/PubliclyAvailableStandards/ISO_19139_Schemas/resources/codelist/gmxCodelists.xml#CI_DateTypeCode" codeListValue="revision">Revisão</gmd:CI_DateTypeCode>
                           </gmd:dateType>
                        </gmd:CI_Date>
                     </gmd:date>
                     <gmd:date>
                        <gmd:CI_Date>
                           <gmd:date>
                              <gco:Date>1985-01-01</gco:Date>
                           </gmd:date>
                           <gmd:dateType>
                              <gmd:CI_DateTypeCode codeList="http://standards.iso.org/ittf/PubliclyAvailableStandards/ISO_19139_Schemas/resources/codelist/gmxCodelists.xml#CI_DateTypeCode" codeListValue="publication">Publicação</gmd:CI_DateTypeCode>
                           </gmd:dateType>
                        </gmd:CI_Date>
                     </gmd:date>
                     <gmd:identifier>
                        <gmd:MD_Identifier>
                           <gmd:code>
                              <gco:CharacterString>http://id.igeo.pt/cdg/f00f3416-2904-47ad-81c1-c51f36449404</gco:CharacterString>
                           </gmd:code>
                        </gmd:MD_Identifier>
                     </gmd:identifier>
                  </gmd:CI_Citation>
               </gmd:citation>
               <gmd:abstract xsi:type="gmd:PT_FreeText_PropertyType">
                  <gco:CharacterString>Cobertura de Sedimentos Superficiais da Plataforma Continental Portuguesa é um CDG criado com base na informação publicada na "Carta dos Sedimentos Superficiais da Plataforma Continental Portuguesa"
A "Carta dos Sedimentos Superficiais da Plataforma Continental Portuguesa" é uma publicação do Instituto Hidrográfico, integralmente financiada pelo Ministério da Defesa Nacional. Esta cartografia, pertencente à “Série Sedimentológica”, é constituída por oito folhas à escala de 1:150000 e respetivas notas explicativas: SED 1 - De Caminha a Espinho (1.ª edição), SED 2 - De Espinho ao Cabo Mondego (1.ª edição), SED 3 - Do Cabo Mondego ao Cabo Carvoeiro (1.ª edição), SED 4 - Do Cabo Carvoeiro ao Cabo da Roca (1.ª edição), SED 5 - Do Cabo da Roca ao Cabo de Sines (1.ª edição), SED 6 - Do Cabo de Sines ao Cabo de S. Vicente (1.ª edição) e SED 7/8 - Do Cabo de S. Vicente ao Rio Guadiana (2.ª edição). À data, todas as oito folhas se encontram publicadas, mas apenas a folha SED 7/8 tem a correspondente nota explicativa produzida e editada.
As campanhas oceanográficas realizadas pelo Instituto Hidrográfico no âmbito do Programa SEPLAT possibilitaram a colheita de mais de 12 mil amostras de sedimentos da superfície do fundo marinho ao longo de toda a costa de Portugal continental e até aos 500m de profundidade, segundo uma malha de amostragem regular com 1 milha náutica de espaçamento médio.
As amostras de sedimento assim obtidas, depois de processadas no laboratório de sedimentologia do Instituto Hidrográfico, forneceram a informação necessária ao desenho e construção das referidas cartas. A classificação adotada na "Carta dos Sedimentos Superficiais da Plataforma Continental Portuguesa" engloba informação sobre o tamanho das partículas e teor em carbonato de cálcio.
O sistema de referência utilizado foi Projeção de Mercator - Elipsoide Internacional - Datum Lisboa.

A aquisição de qualquer uma ou da totalidade das folhas SED da "Carta dos Sedimentos Superficiais da Plataforma Continental Portuguesa" disponíveis em formato analógico (papel), bem como das respetivas notícias explicativas,  pode ser realizada por venda direta na Loja do Navegante ou através da loja online -  http://loja.hidrografico.pt/ln/categoria-produto/cartas-especiais/. O preço de venda encontra-se indicado no sítio da internet da Loja do Navegante.</gco:CharacterString>
                  <gmd:PT_FreeText>
                     <gmd:textGroup>
                        <gmd:LocalisedCharacterString locale="#locale-eng">The "Map of the Superficial Sediments of the Portuguese Continental Shelf" is a publication of the Portuguese Hydrographic Institute (IH-PT), funded entirely by the Ministry of National Defence. This cartography, related to the “Sedimentological Series”, consists of 8 sheets at the scale 1:150000, and their explanation notes: SED 1 - De Caminha a Espinho (1.ª edição), SED 2 - De Espinho ao Cabo Mondego (1.ª edição), SED 3 - Do Cabo Mondego ao Cabo Carvoeiro (1.ª edição), SED 4 - Do Cabo Carvoeiro ao Cabo da Roca (1.ª edição), SED 5 - Do Cabo da Roca ao Cabo de Sines (1.ª edição), SED 6 - Do Cabo de Sines ao Cabo de S. Vicente (1.ª edição) e SED 7/8 - Do Cabo de S. Vicente ao Rio Guadiana (2.ª edição). To date, all of the 8 sheets have been published, but only the SED 7/8 sheet has its explanation note produced and edited.
The oceanographic campaigns, carried out by The Portuguese Hydrographic Institute, under the SEPLAT Program, allowed the collection of twelve thousand samples from the seabed surface, covering the continental shelf off mainland Portugal down to 500m of depth. These sediment samples were collected according to an approximately rectangular sampling mesh with 1 nautical mile of average spacing.
The collected sediment samples were subsequently processed in the sedimentology laboratory, providing the necessary information for the sediment classification and mapping. The classification adopted in the "Map of Superficial Sediments of the Portuguese Continental Shelf" is based on particles grain size and calcium carbonate content.
The reference coordinate system used was Mercator Projection - International Ellipsoid - Datum Lisboa.</gmd:LocalisedCharacterString>
                     </gmd:textGroup>
                  </gmd:PT_FreeText>
               </gmd:abstract>
               <gmd:purpose>
                  <gco:CharacterString>A produção destas cartas teve origem no Programa SEPLAT - "Cartografia Sedimentar da Plataforma Continental Portuguesa", cujo objetivo consistiu na representação cartográfica dos sedimentos superficiais do fundo marinho, substituindo as antigas "Cartas Litológicas Submarinas", publicadas entre 1913 e 1941. Este programa, em desenvolvimento no Instituto Hidrográfico desde 1974, é financiado pela Marinha.</gco:CharacterString>
               </gmd:purpose>
               <gmd:status>
                  <gmd:MD_ProgressCode codeList="http://standards.iso.org/ittf/PubliclyAvailableStandards/ISO_19139_Schemas/resources/codelist/gmxCodelists.xml#MD_ProgressCode" codeListValue="onGoing">Contínuo</gmd:MD_ProgressCode>
               </gmd:status>
               <gmd:pointOfContact>
                  <gmd:CI_ResponsibleParty>
                     <gmd:individualName>
                        <gco:CharacterString>Direcção Técnica</gco:CharacterString>
                     </gmd:individualName>
                     <gmd:organisationName>
                        <gco:CharacterString>Instituto Hidrográfico</gco:CharacterString>
                     </gmd:organisationName>
                     <gmd:contactInfo>
                        <gmd:CI_Contact>
                           <gmd:address>
                              <gmd:CI_Address>
                                 <gmd:deliveryPoint>
                                    <gco:CharacterString>Rua das Trinas, 49</gco:CharacterString>
                                 </gmd:deliveryPoint>
                                 <gmd:city>
                                    <gco:CharacterString>Lisboa</gco:CharacterString>
                                 </gmd:city>
                                 <gmd:postalCode>
                                    <gco:CharacterString>1249-093</gco:CharacterString>
                                 </gmd:postalCode>
                                 <gmd:country>
                                    <gco:CharacterString>Portugal</gco:CharacterString>
                                 </gmd:country>
                                 <gmd:electronicMailAddress>
                                    <gco:CharacterString>ih.snig.metadados@hidrografico.pt</gco:CharacterString>
                                 </gmd:electronicMailAddress>
                              </gmd:CI_Address>
                           </gmd:address>
                        </gmd:CI_Contact>
                     </gmd:contactInfo>
                     <gmd:role>
                        <gmd:CI_RoleCode codeList="http://www.isotc211.org/2005/resources/Codelist/gmxCodelists.xml#CI_RoleCode" codeListValue="pointOfContact" codeSpace="ISOTC211/19115">Contacto</gmd:CI_RoleCode>
                     </gmd:role>
                  </gmd:CI_ResponsibleParty>
               </gmd:pointOfContact>
               <gmd:resourceMaintenance>
                  <gmd:MD_MaintenanceInformation>
                     <gmd:maintenanceAndUpdateFrequency>
                        <gmd:MD_MaintenanceFrequencyCode codeList="http://standards.iso.org/ittf/PubliclyAvailableStandards/ISO_19139_Schemas/resources/codelist/gmxCodelists.xml#MD_MaintenanceFrequencyCode" codeListValue="notPlanned">Não Planeada</gmd:MD_MaintenanceFrequencyCode>
                     </gmd:maintenanceAndUpdateFrequency>
                  </gmd:MD_MaintenanceInformation>
               </gmd:resourceMaintenance>
               <gmd:graphicOverview>
                  <gmd:MD_BrowseGraphic>
                     <gmd:fileName>
                        <gco:CharacterString>http://media.hidrografico.pt/dtcd/HidrograficoMais/f00f3416-2904-47ad-81c1-c51f36449404.jpg</gco:CharacterString>
                     </gmd:fileName>
                  </gmd:MD_BrowseGraphic>
               </gmd:graphicOverview>
               <gmd:descriptiveKeywords>
                  <gmd:MD_Keywords>
                     <gmd:keyword>
                        <gmx:Anchor xlink:href="http://inspire.ec.europa.eu/theme/ge" xlink:type="simple">Geologia</gmx:Anchor>
                     </gmd:keyword>
                     <gmd:type>
                        <gmd:MD_KeywordTypeCode codeList="http://standards.iso.org/ittf/PubliclyAvailableStandards/ISO_19139_Schemas/resourcesFolder/codelist/gmxCodelists.xml#MD_KeywordTypeCode" codeListValue="theme">Tema</gmd:MD_KeywordTypeCode>
                     </gmd:type>
                     <gmd:thesaurusName>
                        <gmd:CI_Citation>
                           <gmd:title>
                              <gmx:Anchor xlink:href="http://www.eionet.europa.eu/gemet/inspire_themes" xlink:type="simple">GEMET - INSPIRE themes, version 1.0</gmx:Anchor>
                           </gmd:title>
                           <gmd:date>
                              <gmd:CI_Date>
                                 <gmd:date>
                                    <gco:Date>2008-06-01</gco:Date>
                                 </gmd:date>
                                 <gmd:dateType>
                                    <gmd:CI_DateTypeCode codeList="http://standards.iso.org/ittf/PubliclyAvailableStandards/ISO_19139_Schemas/resources/codelist/gmxCodelists.xml#CI_DateTypeCode" codeListValue="publication">Publicação</gmd:CI_DateTypeCode>
                                 </gmd:dateType>
                              </gmd:CI_Date>
                           </gmd:date>
                        </gmd:CI_Citation>
                     </gmd:thesaurusName>
                  </gmd:MD_Keywords>
               </gmd:descriptiveKeywords>
               <gmd:descriptiveKeywords>
                  <gmd:MD_Keywords>
                     <gmd:keyword>
                        <gco:CharacterString>Carbonato de cálcio</gco:CharacterString>
                     </gmd:keyword>
                     <gmd:keyword>
                        <gco:CharacterString>Particles grain size</gco:CharacterString>
                     </gmd:keyword>
                     <gmd:keyword>
                        <gco:CharacterString>Calcium carbonate sediment content</gco:CharacterString>
                     </gmd:keyword>
                     <gmd:keyword>
                        <gco:CharacterString>Concentrações de carbono no sedimento</gco:CharacterString>
                     </gmd:keyword>
                     <gmd:keyword>
                        <gco:CharacterString>Classificação do sedimento</gco:CharacterString>
                     </gmd:keyword>
                     <gmd:keyword>
                        <gco:CharacterString>Granulometria sedimentar</gco:CharacterString>
                     </gmd:keyword>
                     <gmd:type>
                        <gmd:MD_KeywordTypeCode codeList="http://www.isotc211.org/2005/resources/Codelist/gmxCodelists.xml#MD_KeywordTypeCode" codeListValue="parameter">parameter</gmd:MD_KeywordTypeCode>
                     </gmd:type>
                  </gmd:MD_Keywords>
               </gmd:descriptiveKeywords>
               <gmd:descriptiveKeywords>
                  <gmd:MD_Keywords>
                     <gmd:keyword>
                        <gco:CharacterString>IH</gco:CharacterString>
                     </gmd:keyword>
                  </gmd:MD_Keywords>
               </gmd:descriptiveKeywords>
               <gmd:descriptiveKeywords>
                  <gmd:MD_Keywords>
                     <gmd:keyword>
                        <gco:CharacterString>Plataforma continental</gco:CharacterString>
                     </gmd:keyword>
                     <gmd:keyword>
                        <gco:CharacterString>Cartas Série SEPLAT</gco:CharacterString>
                     </gmd:keyword>
                     <gmd:keyword>
                        <gco:CharacterString>Sedimento</gco:CharacterString>
                     </gmd:keyword>
                     <gmd:keyword>
                        <gco:CharacterString>Série sedimentológica</gco:CharacterString>
                     </gmd:keyword>
                     <gmd:keyword>
                        <gco:CharacterString>Depósitos sedimentares</gco:CharacterString>
                     </gmd:keyword>
                     <gmd:keyword>
                        <gco:CharacterString>Amostragem de sedimentos marinhos</gco:CharacterString>
                     </gmd:keyword>
                     <gmd:keyword>
                        <gco:CharacterString>Map of the Superficial Sediments of the Portuguese Continental Shelf</gco:CharacterString>
                     </gmd:keyword>
                     <gmd:keyword>
                        <gco:CharacterString>Oceanographic campaigns</gco:CharacterString>
                     </gmd:keyword>
                     <gmd:keyword>
                        <gco:CharacterString>Sediment samples</gco:CharacterString>
                     </gmd:keyword>
                     <gmd:keyword>
                        <gco:CharacterString>Continental shelf</gco:CharacterString>
                     </gmd:keyword>
                     <gmd:keyword>
                        <gco:CharacterString>Sedimentology laboratory</gco:CharacterString>
                     </gmd:keyword>
                     <gmd:keyword>
                        <gco:CharacterString>Upper continental slope</gco:CharacterString>
                     </gmd:keyword>
                     <gmd:keyword>
                        <gco:CharacterString>Sedimentary deposits</gco:CharacterString>
                     </gmd:keyword>
                     <gmd:keyword>
                        <gco:CharacterString>Seabed surface sediments</gco:CharacterString>
                     </gmd:keyword>
                     <gmd:keyword>
                        <gco:CharacterString>Cartografia Oficial</gco:CharacterString>
                     </gmd:keyword>
                     <gmd:keyword>
                        <gco:CharacterString>Cartografia Temática</gco:CharacterString>
                     </gmd:keyword>
                     <gmd:keyword>
                        <gco:CharacterString>Fundo do Mar</gco:CharacterString>
                     </gmd:keyword>
                     <gmd:keyword>
                        <gco:CharacterString>Depósitos sedimentares</gco:CharacterString>
                     </gmd:keyword>
                     <gmd:keyword>
                        <gco:CharacterString>Oceano Atlântico</gco:CharacterString>
                     </gmd:keyword>
                     <gmd:keyword>
                        <gco:CharacterString>Cartografia sedimentar</gco:CharacterString>
                     </gmd:keyword>
                     <gmd:type>
                        <gmd:MD_KeywordTypeCode codeList="http://www.isotc211.org/2005/resources/Codelist/gmxCodelists.xml#MD_KeywordTypeCode" codeListValue="theme">theme</gmd:MD_KeywordTypeCode>
                     </gmd:type>
                  </gmd:MD_Keywords>
               </gmd:descriptiveKeywords>
               <gmd:descriptiveKeywords>
                  <gmd:MD_Keywords>
                     <gmd:keyword>
                        <gco:CharacterString>Programa SEPLAT</gco:CharacterString>
                     </gmd:keyword>
                     <gmd:keyword>
                        <gco:CharacterString>SEPLAT Program</gco:CharacterString>
                     </gmd:keyword>
                     <gmd:type>
                        <gmd:MD_KeywordTypeCode codeList="http://www.isotc211.org/2005/resources/Codelist/gmxCodelists.xml#MD_KeywordTypeCode" codeListValue="project">project</gmd:MD_KeywordTypeCode>
                     </gmd:type>
                  </gmd:MD_Keywords>
               </gmd:descriptiveKeywords>
               <gmd:descriptiveKeywords>
                  <gmd:MD_Keywords>
                     <gmd:keyword>
                        <gco:CharacterString>Geologia marinha e costeira</gco:CharacterString>
                     </gmd:keyword>
                     <gmd:keyword>
                        <gco:CharacterString>Oceanografia</gco:CharacterString>
                     </gmd:keyword>
                     <gmd:type>
                        <gmd:MD_KeywordTypeCode codeList="http://www.isotc211.org/2005/resources/Codelist/gmxCodelists.xml#MD_KeywordTypeCode" codeListValue="discipline">discipline</gmd:MD_KeywordTypeCode>
                     </gmd:type>
                  </gmd:MD_Keywords>
               </gmd:descriptiveKeywords>
               <gmd:descriptiveKeywords>
                  <gmd:MD_Keywords>
                     <gmd:keyword>
                        <gco:CharacterString>INSPIRECORE</gco:CharacterString>
                     </gmd:keyword>
                     <gmd:thesaurusName>
                        <gmd:CI_Citation>
                           <gmd:title>
                              <gco:CharacterString>Options</gco:CharacterString>
                           </gmd:title>
                           <gmd:date>
                              <gmd:CI_Date>
                                 <gmd:date>
                                    <gco:Date>2019-01-01</gco:Date>
                                 </gmd:date>
                                 <gmd:dateType>
                                    <gmd:CI_DateTypeCode codeList="http://standards.iso.org/ittf/PubliclyAvailableStandards/ISO_19139_Schemas/resources/codelist/ML_gmxCodelists.xml#CI_DateTypeCode" codeListValue="publication">publication</gmd:CI_DateTypeCode>
                                 </gmd:dateType>
                              </gmd:CI_Date>
                           </gmd:date>
                        </gmd:CI_Citation>
                     </gmd:thesaurusName>
                  </gmd:MD_Keywords>
               </gmd:descriptiveKeywords>
               <gmd:descriptiveKeywords>
                  <gmd:MD_Keywords>
                     <gmd:keyword>
                        <gco:CharacterString>Grab sampler</gco:CharacterString>
                     </gmd:keyword>
                     <gmd:keyword>
                        <gco:CharacterString>Marine sediments grabs</gco:CharacterString>
                     </gmd:keyword>
                     <gmd:type>
                        <gmd:MD_KeywordTypeCode codeList="http://www.isotc211.org/2005/resources/Codelist/gmxCodelists.xml#MD_KeywordTypeCode" codeListValue="instrument">instrument</gmd:MD_KeywordTypeCode>
                     </gmd:type>
                  </gmd:MD_Keywords>
               </gmd:descriptiveKeywords>
               <gmd:descriptiveKeywords>
                  <gmd:MD_Keywords>
                     <gmd:keyword>
                        <gco:CharacterString>Navio de investigação</gco:CharacterString>
                     </gmd:keyword>
                     <gmd:type>
                        <gmd:MD_KeywordTypeCode codeList="http://www.isotc211.org/2005/resources/Codelist/gmxCodelists.xml#MD_KeywordTypeCode" codeListValue="platform">platform</gmd:MD_KeywordTypeCode>
                     </gmd:type>
                  </gmd:MD_Keywords>
               </gmd:descriptiveKeywords>
               <gmd:descriptiveKeywords>
                  <gmd:MD_Keywords>
                     <gmd:keyword>
                        <gco:CharacterString>Local</gco:CharacterString>
                     </gmd:keyword>
                     <gmd:thesaurusName>
                        <gmd:CI_Citation>
                           <gmd:title>
                              <gco:CharacterString>Spatial scope</gco:CharacterString>
                           </gmd:title>
                           <gmd:date>
                              <gmd:CI_Date>
                                 <gmd:date>
                                    <gco:Date>2019-05-22</gco:Date>
                                 </gmd:date>
                                 <gmd:dateType>
                                    <gmd:CI_DateTypeCode codeList="http://standards.iso.org/ittf/PubliclyAvailableStandards/ISO_19139_Schemas/resources/codelist/ML_gmxCodelists.xml#CI_DateTypeCode" codeListValue="publication">publication</gmd:CI_DateTypeCode>
                                 </gmd:dateType>
                              </gmd:CI_Date>
                           </gmd:date>
                        </gmd:CI_Citation>
                     </gmd:thesaurusName>
                  </gmd:MD_Keywords>
               </gmd:descriptiveKeywords>
               <gmd:descriptiveKeywords>
                  <gmd:MD_Keywords>
                     <gmd:keyword>
                        <gco:CharacterString>Marine regions and units (Marine Strategy Framework Directive)</gco:CharacterString>
                     </gmd:keyword>
                     <gmd:thesaurusName>
                        <gmd:CI_Citation>
                           <gmd:title>
                              <gco:CharacterString>INSPIRE priority data set</gco:CharacterString>
                           </gmd:title>
                           <gmd:date>
                              <gmd:CI_Date>
                                 <gmd:date>
                                    <gco:Date>2018-04-04</gco:Date>
                                 </gmd:date>
                                 <gmd:dateType>
                                    <gmd:CI_DateTypeCode codeList="http://standards.iso.org/ittf/PubliclyAvailableStandards/ISO_19139_Schemas/resources/codelist/ML_gmxCodelists.xml#CI_DateTypeCode" codeListValue="publication">publication</gmd:CI_DateTypeCode>
                                 </gmd:dateType>
                              </gmd:CI_Date>
                           </gmd:date>
                        </gmd:CI_Citation>
                     </gmd:thesaurusName>
                  </gmd:MD_Keywords>
               </gmd:descriptiveKeywords>
               <gmd:resourceConstraints>
                  <gmd:MD_LegalConstraints>
                     <gmd:accessConstraints>
                        <gmd:MD_RestrictionCode codeList="http://standards.iso.org/ittf/PubliclyAvailableStandards/ISO_19139_Schemas/resources/codelist/gmxCodelists.xml#MD_RestrictionCode" codeListValue="otherRestrictions">otherRestrictions</gmd:MD_RestrictionCode>
                     </gmd:accessConstraints>
                     <gmd:otherConstraints>
                        <gmx:Anchor xlink:href="http://inspire.ec.europa.eu/metadata-codelist/LimitationsOnPublicAccess/INSPIRE_Directive_Article13_1e" xlink:type="simple">Acesso público limitado de acordo com o Artigo 13(1)(e) da Diretiva INSPIRE</gmx:Anchor>
                     </gmd:otherConstraints>
                  </gmd:MD_LegalConstraints>
               </gmd:resourceConstraints>
               <gmd:resourceConstraints>
                  <gmd:MD_Constraints>
                     <gmd:useLimitation>
                        <gco:CharacterString>Sem restrições</gco:CharacterString>
                     </gmd:useLimitation>
                  </gmd:MD_Constraints>
               </gmd:resourceConstraints>
               <gmd:resourceConstraints>
                  <gmd:MD_SecurityConstraints>
                     <gmd:classification>
                        <gmd:MD_ClassificationCode codeList="http://www.isotc211.org/2005/resources/Codelist/gmxCodelists.xml#MD_ClassificationCode" codeListValue="unclassified">unclassified</gmd:MD_ClassificationCode>
                     </gmd:classification>
                  </gmd:MD_SecurityConstraints>
               </gmd:resourceConstraints>
               <gmd:resourceConstraints>
                  <gmd:MD_LegalConstraints>
                     <gmd:useConstraints>
                        <gmd:MD_RestrictionCode codeList="http://standards.iso.org/ittf/PubliclyAvailableStandards/ISO_19139_Schemas/resources/codelist/gmxCodelists.xml#MD_RestrictionCode" codeListValue="otherRestrictions">otherRestrictions</gmd:MD_RestrictionCode>
                     </gmd:useConstraints>
                     <gmd:otherConstraints>
                        <gco:CharacterString>Com restrições</gco:CharacterString>
                     </gmd:otherConstraints>
                  </gmd:MD_LegalConstraints>
               </gmd:resourceConstraints>
               <gmd:spatialRepresentationType>
                  <gmd:MD_SpatialRepresentationTypeCode codeList="http://standards.iso.org/ittf/PubliclyAvailableStandards/ISO_19139_Schemas/resources/codelist/gmxCodelists.xml#MD_SpatialRepresentationTypeCode" codeListValue="grid">Matricial</gmd:MD_SpatialRepresentationTypeCode>
               </gmd:spatialRepresentationType>
               <gmd:spatialResolution>
                  <gmd:MD_Resolution>
                     <gmd:equivalentScale>
                        <gmd:MD_RepresentativeFraction>
                           <gmd:denominator>
                              <gco:Integer>150000</gco:Integer>
                           </gmd:denominator>
                        </gmd:MD_RepresentativeFraction>
                     </gmd:equivalentScale>
                  </gmd:MD_Resolution>
               </gmd:spatialResolution>
               <gmd:language>
                  <gmd:LanguageCode codeList="http://www.loc.gov/standards/iso639-2/" codeListValue="por" codeSpace="ISO 639-2">Português</gmd:LanguageCode>
               </gmd:language>
               <gmd:characterSet>
                  <gmd:MD_CharacterSetCode codeList="http://standards.iso.org/ittf/PubliclyAvailableStandards/ISO_19139_Schemas/resources/codelist/gmxCodelists.xml#MD_CharacterSetCode" codeListValue="utf8">utf8</gmd:MD_CharacterSetCode>
               </gmd:characterSet>
               <gmd:topicCategory>
                  <gmd:MD_TopicCategoryCode>geoscientificInformation</gmd:MD_TopicCategoryCode>
               </gmd:topicCategory>
               <gmd:topicCategory>
                  <gmd:MD_TopicCategoryCode>oceans</gmd:MD_TopicCategoryCode>
               </gmd:topicCategory>
               <gmd:topicCategory>
                  <gmd:MD_TopicCategoryCode>environment</gmd:MD_TopicCategoryCode>
               </gmd:topicCategory>
               <gmd:extent>
                  <gmd:EX_Extent>
                     <gmd:geographicElement>
                        <gmd:EX_GeographicBoundingBox>
                           <gmd:extentTypeCode>
                              <gco:Boolean>true</gco:Boolean>
                           </gmd:extentTypeCode>
                           <gmd:westBoundLongitude>
                              <gco:Decimal>-10.23</gco:Decimal>
                           </gmd:westBoundLongitude>
                           <gmd:eastBoundLongitude>
                              <gco:Decimal>-7.37</gco:Decimal>
                           </gmd:eastBoundLongitude>
                           <gmd:southBoundLatitude>
                              <gco:Decimal>36.78</gco:Decimal>
                           </gmd:southBoundLatitude>
                           <gmd:northBoundLatitude>
                              <gco:Decimal>41.86</gco:Decimal>
                           </gmd:northBoundLatitude>
                        </gmd:EX_GeographicBoundingBox>
                     </gmd:geographicElement>
                     <gmd:geographicElement>
                        <gmd:EX_GeographicDescription>
                           <gmd:extentTypeCode>
                              <gco:Boolean>true</gco:Boolean>
                           </gmd:extentTypeCode>
                           <gmd:geographicIdentifier>
                              <gmd:MD_Identifier>
                                 <gmd:code>
                                    <gco:CharacterString>Lisbon - EPSG:4207</gco:CharacterString>
                                 </gmd:code>
                              </gmd:MD_Identifier>
                           </gmd:geographicIdentifier>
                        </gmd:EX_GeographicDescription>
                     </gmd:geographicElement>
                     <gmd:geographicElement>
                        <gmd:EX_GeographicDescription>
                           <gmd:extentTypeCode>
                              <gco:Boolean>true</gco:Boolean>
                           </gmd:extentTypeCode>
                           <gmd:geographicIdentifier>
                              <gmd:MD_Identifier>
                                 <gmd:code>
                                    <gco:CharacterString>Local</gco:CharacterString>
                                 </gmd:code>
                              </gmd:MD_Identifier>
                           </gmd:geographicIdentifier>
                        </gmd:EX_GeographicDescription>
                     </gmd:geographicElement>
                  </gmd:EX_Extent>
               </gmd:extent>
            </gmd:MD_DataIdentification>
         </gmd:identificationInfo>
         <gmd:distributionInfo>
            <gmd:MD_Distribution>
               <gmd:distributionFormat>
                  <gmd:MD_Format>
                     <gmd:name>
                        <gco:CharacterString>TIF</gco:CharacterString>
                     </gmd:name>
                     <gmd:version>
                        <gco:CharacterString>não se aplica</gco:CharacterString>
                     </gmd:version>
                     <gmd:specification>
                        <gco:CharacterString/>
                     </gmd:specification>
                  </gmd:MD_Format>
               </gmd:distributionFormat>
               <gmd:distributionFormat>
                  <gmd:MD_Format>
                     <gmd:name>
                        <gco:CharacterString>JPEG</gco:CharacterString>
                     </gmd:name>
                     <gmd:version>
                        <gco:CharacterString>não se aplica</gco:CharacterString>
                     </gmd:version>
                     <gmd:specification>
                        <gco:CharacterString/>
                     </gmd:specification>
                  </gmd:MD_Format>
               </gmd:distributionFormat>
               <gmd:distributionFormat>
                  <gmd:MD_Format>
                     <gmd:name>
                        <gco:CharacterString>PNG</gco:CharacterString>
                     </gmd:name>
                     <gmd:version>
                        <gco:CharacterString>não se aplica</gco:CharacterString>
                     </gmd:version>
                     <gmd:specification>
                        <gco:CharacterString/>
                     </gmd:specification>
                  </gmd:MD_Format>
               </gmd:distributionFormat>
               <gmd:distributor>
                  <gmd:MD_Distributor>
                     <gmd:distributorContact>
                        <gmd:CI_ResponsibleParty>
                           <gmd:individualName>
                              <gco:CharacterString>Loja do Navegante / Direção Técnica</gco:CharacterString>
                           </gmd:individualName>
                           <gmd:organisationName>
                              <gco:CharacterString>Instituto Hidrográfico</gco:CharacterString>
                           </gmd:organisationName>
                           <gmd:contactInfo>
                              <gmd:CI_Contact>
                                 <gmd:address>
                                    <gmd:CI_Address>
                                       <gmd:deliveryPoint>
                                          <gco:CharacterString>Rua das Trinas, 49</gco:CharacterString>
                                       </gmd:deliveryPoint>
                                       <gmd:city>
                                          <gco:CharacterString>Lisboa</gco:CharacterString>
                                       </gmd:city>
                                       <gmd:postalCode>
                                          <gco:CharacterString>1249-093</gco:CharacterString>
                                       </gmd:postalCode>
                                       <gmd:country>
                                          <gco:CharacterString>Portugal</gco:CharacterString>
                                       </gmd:country>
                                       <gmd:electronicMailAddress>
                                          <gco:CharacterString>lojadonavegante@hidrografico.pt</gco:CharacterString>
                                       </gmd:electronicMailAddress>
                                       <gmd:electronicMailAddress>
                                          <gco:CharacterString>ih.snig.metadados@hidrografico.pt</gco:CharacterString>
                                       </gmd:electronicMailAddress>
                                    </gmd:CI_Address>
                                 </gmd:address>
                                 <gmd:onlineResource>
                                    <gmd:CI_OnlineResource>
                                       <gmd:linkage>
                                          <gmd:URL>http://loja.hidrografico.pt/ln/categoria-produto/cartas-especiais/</gmd:URL>
                                       </gmd:linkage>
                                    </gmd:CI_OnlineResource>
                                 </gmd:onlineResource>
                              </gmd:CI_Contact>
                           </gmd:contactInfo>
                           <gmd:role>
                              <gmd:CI_RoleCode codeList="http://www.isotc211.org/2005/resources/Codelist/gmxCodelists.xml#CI_RoleCode" codeListValue="distributor" codeSpace="ISOTC211/19115">Distribuidor</gmd:CI_RoleCode>
                           </gmd:role>
                        </gmd:CI_ResponsibleParty>
                     </gmd:distributorContact>
                  </gmd:MD_Distributor>
               </gmd:distributor>
               <gmd:transferOptions>
                  <gmd:MD_DigitalTransferOptions>
                     <gmd:onLine>
                        <gmd:CI_OnlineResource>
                           <gmd:linkage>
                              <gmd:URL>https://webgeo2.hidrografico.pt/geoserver/csed/wms?service=WMS&amp;version=1.3.0&amp;request=GetCapabilities</gmd:URL>
                           </gmd:linkage>
                           <gmd:description>
                              <gmx:Anchor xlink:href="http://inspire.ec.europa.eu/metadata-codelist/OnLineDescriptionCode/accessPoint" xlink:type="simple">accessPoint</gmx:Anchor>
                           </gmd:description>
                           <gmd:function>
                              <gmd:CI_OnLineFunctionCode codeList="http://standards.iso.org/ittf/PubliclyAvailableStandards/ISO_19139_Schemas/resources/codelist/gmxCodelists.xml#CI_OnLineFunctionCode" codeListValue="information">Informação</gmd:CI_OnLineFunctionCode>
                           </gmd:function>
                        </gmd:CI_OnlineResource>
                     </gmd:onLine>
                  </gmd:MD_DigitalTransferOptions>
               </gmd:transferOptions>
            </gmd:MD_Distribution>
         </gmd:distributionInfo>
         <gmd:dataQualityInfo>
            <gmd:DQ_DataQuality>
               <gmd:scope>
                  <gmd:DQ_Scope>
                     <gmd:level>
                        <gmd:MD_ScopeCode codeList="http://standards.iso.org/ittf/PubliclyAvailableStandards/ISO_19139_Schemas/resources/codelist/gmxCodelists.xml#MD_ScopeCode" codeListValue="series">Série</gmd:MD_ScopeCode>
                     </gmd:level>
                  </gmd:DQ_Scope>
               </gmd:scope>
               <gmd:report>
                  <gmd:DQ_DomainConsistency>
                     <gmd:result>
                        <gmd:DQ_ConformanceResult>
                           <gmd:specification>
                              <gmd:CI_Citation>
                                 <gmd:title>
                                    <gmx:Anchor xlink:href="http://data.europa.eu/eli/reg/2010/1089" xlink:type="simple">REGULAMENTO (UE) N. o 1089/2010 DA COMISSÃO de 23 de Novembro de 2010 que estabelece as disposições de execução da Directiva 2007/2/CE do Parlamento Europeu e do Conselho relativamente à interoperabilidade dos conjuntos e serviços de dados geográficos</gmx:Anchor>
                                 </gmd:title>
                                 <gmd:date>
                                    <gmd:CI_Date>
                                       <gmd:date>
                                          <gco:Date>2010-12-08</gco:Date>
                                       </gmd:date>
                                       <gmd:dateType>
                                          <gmd:CI_DateTypeCode codeList="http://standards.iso.org/ittf/PubliclyAvailableStandards/ISO_19139_Schemas/resources/codelist/ML_gmxCodelists.xml#CI_DateTypeCode" codeListValue="publication">publication</gmd:CI_DateTypeCode>
                                       </gmd:dateType>
                                    </gmd:CI_Date>
                                 </gmd:date>
                              </gmd:CI_Citation>
                           </gmd:specification>
                           <gmd:explanation>
                              <gco:CharacterString>Ver a especificação citada.</gco:CharacterString>
                           </gmd:explanation>
                           <gmd:pass>
                              <gco:Boolean>false</gco:Boolean>
                           </gmd:pass>
                        </gmd:DQ_ConformanceResult>
                     </gmd:result>
                  </gmd:DQ_DomainConsistency>
               </gmd:report>
               <gmd:lineage>
                  <gmd:LI_Lineage>
                     <gmd:statement xsi:type="gmd:PT_FreeText_PropertyType">
                        <gco:CharacterString>As “Cartas dos Sedimentos Superficiais da Plataforma Continental Portuguesa” constituem o principal produto do Programa SEPLAT, financiado pelo Ministério da Defesa Nacional (MDN) desde 1974. O objetivo primordial deste programa é a representação cartográfica dos depósitos sedimentares que se encontram nos fundos marinhos da plataforma continental e vertente continental superior. O programa foi criado para substituir as antigas "Cartas Litológicas Submarinas", publicadas entre 1913 e 1941.
As campanhas oceanográficas realizadas no âmbito do Programa SEPLAT possibilitaram a colheita de mais de 12000 amostras de sedimentos superficiais ao longo de toda a costa de Portugal continental (do Minho ao Algarve), desde a linha de costa até aos 500m de profundidade, utilizando diversos colhedores superficiais de sedimentos e segundo uma malha de amostragem regular com 1 milha náutica de espaçamento médio. As amostras de sedimento assim obtidas, depois de devidamente posicionadas e referenciadas, foram processadas no Laboratório de Sedimentologia do Instituto Hidrográfico, tendo em vista a aplicação do esquema classificativo adotado nas cartas sedimentológicas “Carta dos Sedimentos Superficiais da Plataforma Continental Portuguesa”, baseado no tamanho do grão e no teor em carbonato de cálcio.</gco:CharacterString>
                        <gmd:PT_FreeText>
                           <gmd:textGroup>
                              <gmd:LocalisedCharacterString locale="#locale-eng">The "Map of the Superficial Sediments of the Portuguese Continental Shelf" is the main product of the SEPLAT Program, funded by the Portuguese Ministry of National Defense since 1974. This program is addressed to the cartographic representation of the sedimentary deposits of the seabed of the continental shelf and the upper continental slope. The program was created to replace the old "Submarine Lithological Maps", published between 1913 and 1941.
The oceanographic campaigns carried out under the SEPLAT program enabled the collection of more than 12000 samples of surface sediments along the entire coast off mainland Portugal (from Minho to the Algarve) from the coastline down to 500 m of depth, using different types of grabs, following a regular sampling distance, with 1 nautical mile average spacing. After being georeferenced, the collected sediment samples were processed in the Sedimentological Laboratory of the Portuguese Hydrographic Institute (IH-PT) in order to apply the classification scheme adopted in the “Map of the Superficial Sediments of the Portuguese Continental Shelf”, based on the particles grain size and their calcium carbonate content.</gmd:LocalisedCharacterString>
                           </gmd:textGroup>
                        </gmd:PT_FreeText>
                     </gmd:statement>
                  </gmd:LI_Lineage>
               </gmd:lineage>
            </gmd:DQ_DataQuality>
         </gmd:dataQualityInfo>
      </gmd:MD_Metadata>